filenames/__init__.py
filenames/__main__.py
filenames/filenames.py
filenames-0.1.3.dist-info/LICENSE
filenames-0.1.3.dist-info/METADATA
filenames-0.1.3.dist-info/WHEEL
filenames-0.1.3.dist-info/entry_points.txt
filenames-0.1.3.dist-info/top_level.txt
filenames-0.1.3.dist-info/RECORD
